grai_source_snowflake/__init__.py
grai_source_snowflake/adapters.py
grai_source_snowflake/base.py
grai_source_snowflake/loader.py
grai_source_snowflake/models.py
grai_source_snowflake/package_definitions.py
grai_source_snowflake-0.1.2.dist-info/METADATA
grai_source_snowflake-0.1.2.dist-info/WHEEL
grai_source_snowflake-0.1.2.dist-info/RECORD
